cyclops/__init__.py
cyclops/core/__init__.py
cyclops/core/agent.py
cyclops/core/memory.py
cyclops/core/types.py
cyclops/mcp/__init__.py
cyclops/mcp/client.py
cyclops/mcp/server.py
cyclops/mcp/tools.py
cyclops/toolkit/__init__.py
cyclops/toolkit/decorators.py
cyclops/toolkit/plugins.py
cyclops/toolkit/registry.py
cyclops/toolkit/tool.py
cyclops/toolkit/types.py
cyclops/utils/__init__.py
cyclops/utils/config.py
cyclops/utils/logging.py
cyclops_ai-0.1.0.dist-info/METADATA
cyclops_ai-0.1.0.dist-info/WHEEL
cyclops_ai-0.1.0.dist-info/licenses/LICENSE
cyclops_ai-0.1.0.dist-info/RECORD
