Metadata-Version: 2.4
Name: cyclops-ai
Version: 0.1.0
Summary: Core agent framework with MCP toolkit support
Project-URL: Homepage, https://github.com/gopalji/cyclops
Project-URL: Repository, https://github.com/gopalji/cyclops
Project-URL: Issues, https://github.com/gopalji/cyclops/issues
Author: Gopalji Gaur
License: MIT
License-File: LICENSE
Keywords: agents,ai,litellm,llm,mcp,tools
Classifier: Development Status :: 3 - Alpha
Classifier: Intended Audience :: Developers
Classifier: License :: OSI Approved :: MIT License
Classifier: Programming Language :: Python :: 3
Classifier: Programming Language :: Python :: 3.10
Classifier: Programming Language :: Python :: 3.11
Classifier: Programming Language :: Python :: 3.12
Classifier: Topic :: Scientific/Engineering :: Artificial Intelligence
Classifier: Topic :: Software Development :: Libraries :: Python Modules
Requires-Python: >=3.10
Requires-Dist: hatchling>=1.27.0
Requires-Dist: litellm>=1.79.1
Requires-Dist: mcp>=1.21.0
Requires-Dist: pluggy>=1.6.0
Requires-Dist: pydantic>=2.12.4
